pypowerworld/__init__.py
pypowerworld/__version__.py
pypowerworld/pypowerworld.py
pypowerworld-0.3.6.dist-info/METADATA
pypowerworld-0.3.6.dist-info/RECORD
pypowerworld-0.3.6.dist-info/WHEEL
pypowerworld-0.3.6.dist-info/top_level.txt
