Metadata-Version: 2.1
Name: pypowerworld
Version: 0.3.6
Summary: Powerworld COM wrapper for Python
Home-page: https://github.com/jessemarkboyd/pypowerworld
Author: Jesse Boyd
Author-email: jessemarkboyd@gmail.com
License: MIT
Download-URL: https://github.com/jessemarkboyd/pypowerworld/tarball/0.3.6
Platform: UNKNOWN
Classifier: License :: OSI Approved :: MIT License
Classifier: Programming Language :: Python
Classifier: Programming Language :: Python :: 2.6
Classifier: Programming Language :: Python :: 2.7
Classifier: Programming Language :: Python :: 3
Classifier: Programming Language :: Python :: 3.3
Classifier: Programming Language :: Python :: 3.4
Classifier: Programming Language :: Python :: 3.5
Classifier: Programming Language :: Python :: 3.6
Classifier: Programming Language :: Python :: Implementation :: CPython
Classifier: Programming Language :: Python :: Implementation :: PyPy
Requires-Dist: pandas
Requires-Dist: numpy
Requires-Dist: pypiwin32
Requires-Dist: pywin32
